celery_pipeline-0.15.dist-info/DESCRIPTION.rst
celery_pipeline-0.15.dist-info/METADATA
celery_pipeline-0.15.dist-info/RECORD
celery_pipeline-0.15.dist-info/WHEEL
celery_pipeline-0.15.dist-info/metadata.json
celery_pipeline-0.15.dist-info/pbr.json
celery_pipeline-0.15.dist-info/top_level.txt
pipeline/__init__.py
pipeline/actions.py
pipeline/bases.py
pipeline/command.py
pipeline/context.py
pipeline/criteria.py
pipeline/eval.py
pipeline/executor.py
pipeline/pipeline.py
pipeline/registry.py
pipeline/signals.py
pipeline/tasks.py
pipeline/utils.py
pipeline/workspace.py
