Metadata-Version: 2.0
Name: celery-pipeline
Version: 0.15
Summary: Runtime-configurable execution pipeline built on celery.
Home-page: https://github.com/mikewaters/pipeline
Author: Mike Waters
Author-email: robert.waters@gmail.com
License: BSD
Keywords: pipeline
Platform: UNKNOWN
Classifier: Development Status :: 2 - Pre-Alpha
Classifier: Intended Audience :: Developers
Classifier: License :: OSI Approved :: BSD License
Classifier: Natural Language :: English
Classifier: Programming Language :: Python :: 3.4
Requires-Dist: cached-property
Requires-Dist: celery (==3.1.18)
Requires-Dist: commandsession (==0.3)
Requires-Dist: github3.py (==1.0.0a2)
Requires-Dist: jenkinsapi
Requires-Dist: jinja2
Requires-Dist: jsonpickle
Requires-Dist: pip
Requires-Dist: redis
Requires-Dist: tox
